st_textnav_components/__init__.py
st_textnav_components/frontend/build/asset-manifest.json
st_textnav_components/frontend/build/bootstrap.min.css
st_textnav_components/frontend/build/index.html
st_textnav_components/frontend/build/precache-manifest.e80c861d8cce26162e6362a910c1ae2b.js
st_textnav_components/frontend/build/service-worker.js
st_textnav_components/frontend/build/static/js/2.c12c44ef.chunk.js
st_textnav_components/frontend/build/static/js/2.c12c44ef.chunk.js.LICENSE.txt
st_textnav_components/frontend/build/static/js/2.c12c44ef.chunk.js.map
st_textnav_components/frontend/build/static/js/main.c0c60160.chunk.js
st_textnav_components/frontend/build/static/js/main.c0c60160.chunk.js.map
st_textnav_components/frontend/build/static/js/runtime-main.5875292e.js
st_textnav_components/frontend/build/static/js/runtime-main.5875292e.js.map
st_textnav_components-0.0.1.dist-info/LICENSE
st_textnav_components-0.0.1.dist-info/METADATA
st_textnav_components-0.0.1.dist-info/WHEEL
st_textnav_components-0.0.1.dist-info/top_level.txt
st_textnav_components-0.0.1.dist-info/RECORD
